crpylib/__init__.py
crpylib/aes.py
crpylib/jwe.py
crpylib/jwt.py
crpylib/key.py
crpylib/sgn.py
crpylib/utl.py
crpylib-0.1.0.dist-info/METADATA
crpylib-0.1.0.dist-info/WHEEL
crpylib-0.1.0.dist-info/RECORD
